Kurdish_Characters/Kurdish_Characters.py
Kurdish_Characters/__init__.py
kurdish_characters-1.0.1.dist-info/licenses/LICENSE
kurdish_characters-1.0.1.dist-info/METADATA
kurdish_characters-1.0.1.dist-info/WHEEL
kurdish_characters-1.0.1.dist-info/top_level.txt
kurdish_characters-1.0.1.dist-info/RECORD
