Metadata-Version: 2.4
Name: Kurdish_Characters
Version: 1.0.1
Summary: A Python library to properly display Kurdish characters in tkinter and other interfaces
Home-page: https://github.com/neshwantaha/Kurdish_Characters
Author: Nashwan Taha Nheli
Author-email: Nashwan Taha Nheli <neshwantaha@gmail.com>
License: MIT
Project-URL: Homepage, https://github.com/neshwantaha/Kurdish_Characters
Project-URL: Bug Reports, https://github.com/neshwantaha/Kurdish_Characters/issues
Project-URL: Source, https://github.com/neshwantaha/Kurdish_Characters
Keywords: kurdish,text,tkinter,unicode,font,display
Classifier: Development Status :: 4 - Beta
Classifier: Intended Audience :: Developers
Classifier: License :: OSI Approved :: MIT License
Classifier: Operating System :: OS Independent
Classifier: Programming Language :: Python :: 3
Classifier: Programming Language :: Python :: 3.6
Classifier: Programming Language :: Python :: 3.7
Classifier: Programming Language :: Python :: 3.8
Classifier: Programming Language :: Python :: 3.9
Classifier: Programming Language :: Python :: 3.10
Classifier: Programming Language :: Python :: 3.11
Classifier: Topic :: Software Development :: Libraries :: Python Modules
Classifier: Topic :: Text Processing :: Linguistic
Requires-Python: >=3.6
License-File: LICENSE
Dynamic: author
Dynamic: home-page
Dynamic: license-file
Dynamic: requires-python
